[
  {
    "id": "c6bfc845-b1dc-43e9-8f79-fd4854842949",
    "source": "Salvage Union Workshop Manual",
    "name": "Wastelander",
    "description": "Represents the myriad of common denizens of the wastelands.",
    "abilities": [
      {
        "name": "Improvised Melee Weapon",
        "range": "Close",
        "damage": {
          "amount": 2,
          "type": "HP"
        },
        "traits": [
          {
            "type": "melee"
          }
        ]
      },
      {
        "name": "Salvaging Tools"
      }
    ],
    "hitPoints": 2,
    "page": 53
  },
  {
    "id": "bb1b8558-1bca-4db8-8d13-f02fc344d327",
    "source": "Salvage Union Workshop Manual",
    "name": "Raider",
    "description": "Wastelanders who take what they need by force.",
    "abilities": [
      {
        "name": "Improvised Firearm",
        "range": "Close",
        "damage": {
          "amount": 3,
          "type": "HP"
        },
        "traits": [
          {
            "type": "ballistic"
          },
          {
            "type": "unwieldy"
          }
        ]
      }
    ],
    "hitPoints": 3,
    "page": 46
  },
  {
    "id": "28015ce1-8440-471c-b97e-bb4ff114a667",
    "source": "Salvage Union Workshop Manual",
    "name": "Trooper",
    "description": "Combat trained troops deployed in a wide range of roles.",
    "abilities": [
      {
        "name": "Rifle",
        "range": "Medium",
        "damage": {
          "amount": 5,
          "type": "HP"
        },
        "traits": [
          {
            "type": "ballistic"
          }
        ]
      },
      {
        "name": "Portable Comms Unit"
      }
    ],
    "hitPoints": 5,
    "page": 274
  },
  {
    "id": "5b1e5b18-c023-4e7c-a6b9-c6a22cb6e48d",
    "source": "Salvage Union Workshop Manual",
    "name": "Veteran",
    "description": "A well trained and seasoned soldier deployed on difficult operations.",
    "abilities": [
      {
        "name": "Green Laser Rifle",
        "range": "Medium",
        "damage": {
          "amount": 5,
          "type": "HP"
        },
        "traits": [
          {
            "type": "energy"
          }
        ]
      },
      {
        "name": "Portable Comms Unit"
      }
    ],
    "hitPoints": 9,
    "page": 52
  },
  {
    "id": "ad0a3127-2fb2-4d38-af8e-7fc76d9d05d9",
    "source": "Salvage Union Workshop Manual",
    "name": "Combat Pilot",
    "description": "A combat trained Mech Pilot, such as a Union Salvager.",
    "abilities": [
      {
        "name": "Pistol",
        "range": "Close",
        "damage": {
          "amount": 3,
          "type": "HP"
        },
        "traits": [
          {
            "type": "ballistic"
          }
        ]
      },
      {
        "name": "Portable Comms Unit"
      }
    ],
    "hitPoints": 10,
    "page": 57
  },
  {
    "id": "15ff8ca3-a759-4c39-a546-1cac319ffc4e",
    "source": "Salvage Union Workshop Manual",
    "name": "Ace",
    "description": "A veteran Mech Pilot, usually with Corpo training.",
    "abilities": [
      {
        "name": "Sniper Rifle",
        "range": "Long",
        "damage": {
          "amount": 6,
          "type": "HP"
        },
        "traits": [
          {
            "type": "ballistic"
          }
        ]
      },
      {
        "name": "Portable Comms Unit"
      }
    ],
    "hitPoints": 16,
    "page": 12
  }
]
